lioness/__init__.py
lioness/conf_default/logging.ini
lioness/nodes/__init__.py
lioness/nodes/download_and_merge.py
lioness/nodes/project_logging.py
lioness/pipelines/__init__.py
lioness/pipelines/download_and_merge.py
lioness/pipelines/streamlit_app.py
pytube_lioness-0.0.4.dist-info/METADATA
pytube_lioness-0.0.4.dist-info/WHEEL
pytube_lioness-0.0.4.dist-info/RECORD
